feedmark/__init__.py
feedmark/checkers.py
feedmark/feeds.py
feedmark/loader.py
feedmark/main.py
feedmark/models.py
feedmark/parser.py
feedmark/renderer.py
feedmark/tests.py
feedmark/utils.py
feedmark/formats/__init__.py
feedmark/formats/atom.py
feedmark/formats/markdown.py
marko/__init__.py
marko/__main__.py
marko/ast_renderer.py
marko/block.py
marko/cli.py
marko/element.py
marko/helpers.py
marko/html_renderer.py
marko/inline.py
marko/inline_parser.py
marko/md_renderer.py
marko/parser.py
marko/patterns.py
marko/py.typed
marko/renderer.py
marko/source.py
marko/ext/__init__.py
marko/ext/codehilite.py
marko/ext/footnote.py
marko/ext/latex_renderer.py
marko/ext/pangu.py
marko/ext/toc.py
marko/ext/gfm/__init__.py
marko/ext/gfm/elements.py
marko/ext/gfm/renderer.py
feedmark-0.17.dist-info/METADATA
feedmark-0.17.dist-info/WHEEL
feedmark-0.17.dist-info/entry_points.txt
feedmark-0.17.dist-info/top_level.txt
feedmark-0.17.dist-info/RECORD
