Metadata-Version: 2.4
Name: Feedmark
Version: 0.17
Summary: Feedmark: a curation-oriented subset of Markdown, and tools for processing it
Author-email: Chris Pressey <packages@catseye.tc>
Project-URL: website, https://catseye.tc/node/Feedmark
Classifier: License :: OSI Approved :: MIT License
Classifier: Operating System :: OS Independent
Classifier: Programming Language :: Python :: 3
Requires-Python: >=3.9
Requires-Dist: atomize==0.2.0
Requires-Dist: python-slugify==8.0.4
